text_grader/__init__.py
text_grader/grader.py
text_grader-0.1.2.dist-info/METADATA
text_grader-0.1.2.dist-info/WHEEL
text_grader-0.1.2.dist-info/top_level.txt
text_grader-0.1.2.dist-info/RECORD
